wmclient/__init__.py
wmclient/test_data.py
wmclient/test_wmclient.py
wmclient/wmclient.py
wmclient-2.3.1.dist-info/LICENSE.txt
wmclient-2.3.1.dist-info/METADATA
wmclient-2.3.1.dist-info/WHEEL
wmclient-2.3.1.dist-info/top_level.txt
wmclient-2.3.1.dist-info/RECORD
