Metadata-Version: 2.1
Name: wmclient
Version: 2.3.1
Summary: WURFL Microservice client for Python
Author-email: "Scientiamobile Inc." <support@scientiamobile.com>
License: apache-2.0
Project-URL: Homepage, https://github.com/WURFL/wurfl-microservice-client-python
Keywords: device,mobile,device detection,analytics
Classifier: License :: OSI Approved :: Apache Software License
Classifier: Development Status :: 5 - Production/Stable
Classifier: Intended Audience :: Developers
Classifier: Topic :: Software Development :: Build Tools
Classifier: Programming Language :: Python
Classifier: Programming Language :: Python :: 3.5
Classifier: Programming Language :: Python :: 3.6
Classifier: Programming Language :: Python :: 3.7
Classifier: Programming Language :: Python :: 3.8
Classifier: Programming Language :: Python :: 3.9
Classifier: Programming Language :: Python :: 3.10
Classifier: Programming Language :: Python :: 3.11
Classifier: Programming Language :: Python :: 3.12
Classifier: Programming Language :: Python :: 3.13
License-File: LICENSE.txt
Requires-Dist: pycurl
Requires-Dist: pylru
